winrichnotify/__init__.py
winrichnotify/data/python.ico
winrichnotify-0.1.0.dist-info/LICENSE
winrichnotify-0.1.0.dist-info/METADATA
winrichnotify-0.1.0.dist-info/WHEEL
winrichnotify-0.1.0.dist-info/RECORD
