Metadata-Version: 2.1
Name: winrichnotify
Version: 0.1.0
Summary: An easy-to-use Python library for displaying rich notifications on Windows 10/11
Home-page: https://github.com/HarryPeach/WindowsRichNotifications
License: MIT
Keywords: notifications,windows
Author: Harry Peach
Requires-Python: >=3.10,<4.0
Classifier: Development Status :: 3 - Alpha
Classifier: Environment :: Win32 (MS Windows)
Classifier: License :: OSI Approved :: MIT License
Classifier: Operating System :: Microsoft
Classifier: Programming Language :: Python :: 3
Classifier: Programming Language :: Python :: 3.10
Classifier: Programming Language :: Python :: 3.11
Classifier: Topic :: Utilities
Requires-Dist: pypiwin32 (>=223,<224)
Project-URL: Repository, https://github.com/HarryPeach/WindowsRichNotifications
